{
"meta":{"test_sets":[],"test_metrics":[],"learn_metrics":[{"best_value":"Min","name":"MAE"}],"launch_mode":"Train","parameters":"","iteration_count":300,"learn_sets":["learn"],"name":"experiment"},
"iterations":[
{"learn":[188135.6826],"iteration":0,"passed_time":0.0009450727895,"remaining_time":0.2825767641},
{"learn":[187392.7437],"iteration":1,"passed_time":0.001865564105,"remaining_time":0.2779690517},
{"learn":[186644.8207],"iteration":2,"passed_time":0.00283093508,"remaining_time":0.280262573},
{"learn":[185560.5028],"iteration":3,"passed_time":0.003678692877,"remaining_time":0.2722232729},
{"learn":[185333.0749],"iteration":4,"passed_time":0.00440130605,"remaining_time":0.259677057},
{"learn":[184354.285],"iteration":5,"passed_time":0.005651308618,"remaining_time":0.2769141223},
{"learn":[183484.0163],"iteration":6,"passed_time":0.006571380589,"remaining_time":0.2750592161},
{"learn":[183087.0308],"iteration":7,"passed_time":0.007350204323,"remaining_time":0.2682824578},
{"learn":[182151.4379],"iteration":8,"passed_time":0.008222088837,"remaining_time":0.265847539},
{"learn":[181774.7003],"iteration":9,"passed_time":0.009201913253,"remaining_time":0.2668554843},
{"learn":[181094.078],"iteration":10,"passed_time":0.01001838489,"remaining_time":0.263210294},
{"learn":[180279.7984],"iteration":11,"passed_time":0.01060926879,"remaining_time":0.2546224509},
{"learn":[179545.9783],"iteration":12,"passed_time":0.01171659585,"remaining_time":0.2586663854},
{"learn":[178756.7836],"iteration":13,"passed_time":0.01248277399,"remaining_time":0.2550052401},
{"learn":[178102.3357],"iteration":14,"passed_time":0.01333550877,"remaining_time":0.2533746666},
{"learn":[177436.8437],"iteration":15,"passed_time":0.01399188921,"remaining_time":0.2483560335},
{"learn":[176818.7759],"iteration":16,"passed_time":0.01468676296,"remaining_time":0.2444914069},
{"learn":[176126.9326],"iteration":17,"passed_time":0.01544476069,"remaining_time":0.2419679175},
{"learn":[175484.5373],"iteration":18,"passed_time":0.01613262037,"remaining_time":0.2385929645},
{"learn":[174876.1162],"iteration":19,"passed_time":0.01695696005,"remaining_time":0.2373974407},
{"learn":[174178.4682],"iteration":20,"passed_time":0.01779926822,"remaining_time":0.2364759921},
{"learn":[173375.7446],"iteration":21,"passed_time":0.0188881631,"remaining_time":0.2386776973},
{"learn":[172607.8998],"iteration":22,"passed_time":0.01944582104,"remaining_time":0.2341953229},
{"learn":[171942.1001],"iteration":23,"passed_time":0.02044253967,"remaining_time":0.2350892062},
{"learn":[171261.0858],"iteration":24,"passed_time":0.02099224533,"remaining_time":0.2309146986},
{"learn":[170654.9079],"iteration":25,"passed_time":0.0216627702,"remaining_time":0.2282922706},
{"learn":[170251.1613],"iteration":26,"passed_time":0.02246538592,"remaining_time":0.2271500132},
{"learn":[169484.6637],"iteration":27,"passed_time":0.02310422616,"remaining_time":0.2244410542},
{"learn":[168794.2361],"iteration":28,"passed_time":0.02416620875,"remaining_time":0.2258290542},
{"learn":[167949.4149],"iteration":29,"passed_time":0.02498358916,"remaining_time":0.2248523024},
{"learn":[167288.9947],"iteration":30,"passed_time":0.02581787497,"remaining_time":0.224032528},
{"learn":[166731.3107],"iteration":31,"passed_time":0.02677947556,"remaining_time":0.2242781078},
{"learn":[166129.8421],"iteration":32,"passed_time":0.02776746249,"remaining_time":0.2246640147},
{"learn":[165415.5935],"iteration":33,"passed_time":0.02860007577,"remaining_time":0.2237535339},
{"learn":[164825.2016],"iteration":34,"passed_time":0.02920468549,"remaining_time":0.2211211901},
{"learn":[164181.8767],"iteration":35,"passed_time":0.02999623571,"remaining_time":0.2199723952},
{"learn":[163681.403],"iteration":36,"passed_time":0.03068225586,"remaining_time":0.2180927917},
{"learn":[163649.3838],"iteration":37,"passed_time":0.03112904258,"remaining_time":0.2146265567},
{"learn":[163151.7791],"iteration":38,"passed_time":0.03182101222,"remaining_time":0.2129560049},
{"learn":[162669.5849],"iteration":39,"passed_time":0.03254093301,"remaining_time":0.2115160646},
{"learn":[162201.2987],"iteration":40,"passed_time":0.03341151327,"remaining_time":0.211062974},
{"learn":[161898.5394],"iteration":41,"passed_time":0.03399223372,"remaining_time":0.2088094357},
{"learn":[161351.4819],"iteration":42,"passed_time":0.03474013324,"remaining_time":0.2076328893},
{"learn":[160710.1413],"iteration":43,"passed_time":0.03551380144,"remaining_time":0.2066257538},
{"learn":[160346.0117],"iteration":44,"passed_time":0.03617802681,"remaining_time":0.2050088186},
{"learn":[159862.2174],"iteration":45,"passed_time":0.03707201698,"remaining_time":0.2047020068},
{"learn":[159635.7885],"iteration":46,"passed_time":0.03778165319,"remaining_time":0.2033778352},
{"learn":[159080.692],"iteration":47,"passed_time":0.03837091375,"remaining_time":0.2014472972},
{"learn":[158502.3151],"iteration":48,"passed_time":0.03934536346,"remaining_time":0.2015446169},
{"learn":[157958.2297],"iteration":49,"passed_time":0.03997767831,"remaining_time":0.1998883916},
{"learn":[157530.2523],"iteration":50,"passed_time":0.04074313704,"remaining_time":0.198922375},
{"learn":[157099.1156],"iteration":51,"passed_time":0.04174905481,"remaining_time":0.1991108768},
{"learn":[156672.9655],"iteration":52,"passed_time":0.04236981549,"remaining_time":0.1974593288},
{"learn":[156047.1195],"iteration":53,"passed_time":0.04309785704,"remaining_time":0.1963346821},
{"learn":[155650.4595],"iteration":54,"passed_time":0.04399365133,"remaining_time":0.1959717196},
{"learn":[155066.3257],"iteration":55,"passed_time":0.04492554996,"remaining_time":0.1957470391},
{"learn":[154953.0998],"iteration":56,"passed_time":0.04547272016,"remaining_time":0.193857386},
{"learn":[154451.3029],"iteration":57,"passed_time":0.04607549707,"remaining_time":0.1922460395},
{"learn":[153903.1673],"iteration":58,"passed_time":0.04712027121,"remaining_time":0.1924743281},
{"learn":[153423.992],"iteration":59,"passed_time":0.04768336759,"remaining_time":0.1907334704},
{"learn":[152948.519],"iteration":60,"passed_time":0.04846869248,"remaining_time":0.1899019263},
{"learn":[152677.0092],"iteration":61,"passed_time":0.04925548751,"remaining_time":0.1890775166},
{"learn":[152334.5285],"iteration":62,"passed_time":0.050228627,"remaining_time":0.1889553111},
{"learn":[151882.1054],"iteration":63,"passed_time":0.0510730852,"remaining_time":0.1883320017},
{"learn":[151432.4605],"iteration":64,"passed_time":0.05194663256,"remaining_time":0.1878070562},
{"learn":[151001.1107],"iteration":65,"passed_time":0.05290244507,"remaining_time":0.1875632143},
{"learn":[150510.8802],"iteration":66,"passed_time":0.05363649016,"remaining_time":0.1865268986},
{"learn":[150188.4261],"iteration":67,"passed_time":0.0545712463,"remaining_time":0.1861842521},
{"learn":[149684.493],"iteration":68,"passed_time":0.05522631913,"remaining_time":0.1848881119},
{"learn":[149269.0927],"iteration":69,"passed_time":0.05623447863,"remaining_time":0.1847704298},
{"learn":[148854.6113],"iteration":70,"passed_time":0.05694873658,"remaining_time":0.1836797278},
{"learn":[148660.7033],"iteration":71,"passed_time":0.05784573746,"remaining_time":0.1831781686},
{"learn":[148409.2736],"iteration":72,"passed_time":0.05859171806,"remaining_time":0.1821961644},
{"learn":[148112.9602],"iteration":73,"passed_time":0.05941654231,"remaining_time":0.1814613319},
{"learn":[147808.8644],"iteration":74,"passed_time":0.06020345103,"remaining_time":0.1806103531},
{"learn":[147469.0396],"iteration":75,"passed_time":0.06081932344,"remaining_time":0.1792569533},
{"learn":[147173.6055],"iteration":76,"passed_time":0.06166723817,"remaining_time":0.1785947287},
{"learn":[146874.2573],"iteration":77,"passed_time":0.06236906448,"remaining_time":0.1775119527},
{"learn":[146635.3813],"iteration":78,"passed_time":0.06311098357,"remaining_time":0.1765509794},
{"learn":[146349.2122],"iteration":79,"passed_time":0.06414547797,"remaining_time":0.1764000644},
{"learn":[146036.7897],"iteration":80,"passed_time":0.06502434412,"remaining_time":0.17580656},
{"learn":[145642.3694],"iteration":81,"passed_time":0.06580018248,"remaining_time":0.1749321925},
{"learn":[145450.58],"iteration":82,"passed_time":0.06693391676,"remaining_time":0.1749959029},
{"learn":[145092.932],"iteration":83,"passed_time":0.06758463734,"remaining_time":0.1737890675},
{"learn":[144831.0493],"iteration":84,"passed_time":0.06857574607,"remaining_time":0.1734562989},
{"learn":[144616.2271],"iteration":85,"passed_time":0.06950300394,"remaining_time":0.1729493354},
{"learn":[144301.307],"iteration":86,"passed_time":0.07017312214,"remaining_time":0.1718031611},
{"learn":[144099.0521],"iteration":87,"passed_time":0.07103175124,"remaining_time":0.1711219462},
{"learn":[143921.0297],"iteration":88,"passed_time":0.07173711049,"remaining_time":0.1700733743},
{"learn":[143545.9016],"iteration":89,"passed_time":0.07237133607,"remaining_time":0.1688664508},
{"learn":[143283.7542],"iteration":90,"passed_time":0.07311454376,"remaining_time":0.1679224137},
{"learn":[142878.4031],"iteration":91,"passed_time":0.0740990436,"remaining_time":0.1675282725},
{"learn":[142774.2912],"iteration":92,"passed_time":0.07496401171,"remaining_time":0.1668553809},
{"learn":[142462.1354],"iteration":93,"passed_time":0.07581887154,"remaining_time":0.1661562504},
{"learn":[142416.1279],"iteration":94,"passed_time":0.07659262325,"remaining_time":0.1652788186},
{"learn":[142222.3155],"iteration":95,"passed_time":0.07722881137,"remaining_time":0.1641112242},
{"learn":[141987.9549],"iteration":96,"passed_time":0.07816710977,"remaining_time":0.163586838},
{"learn":[141594.0232],"iteration":97,"passed_time":0.07878858165,"remaining_time":0.162400954},
{"learn":[141328.5671],"iteration":98,"passed_time":0.07940898374,"remaining_time":0.1612243003},
{"learn":[141192.3633],"iteration":99,"passed_time":0.08041918331,"remaining_time":0.1608383666},
{"learn":[140933.7093],"iteration":100,"passed_time":0.08100585586,"remaining_time":0.1596055972},
{"learn":[140642.151],"iteration":101,"passed_time":0.08170915155,"remaining_time":0.1586118824},
{"learn":[140459.9267],"iteration":102,"passed_time":0.08273199821,"remaining_time":0.1582349869},
{"learn":[140186.5455],"iteration":103,"passed_time":0.0837422276,"remaining_time":0.1578218905},
{"learn":[139835.8941],"iteration":104,"passed_time":0.08442736507,"remaining_time":0.156793678},
{"learn":[139524.1186],"iteration":105,"passed_time":0.08496011426,"remaining_time":0.1554930393},
{"learn":[139222.3113],"iteration":106,"passed_time":0.08561609362,"remaining_time":0.1544290287},
{"learn":[138948.5469],"iteration":107,"passed_time":0.08646193473,"remaining_time":0.1537101062},
{"learn":[138772.3741],"iteration":108,"passed_time":0.08705829509,"remaining_time":0.1525516914},
{"learn":[138573.8554],"iteration":109,"passed_time":0.08782544984,"remaining_time":0.1516985043},
{"learn":[138324.8695],"iteration":110,"passed_time":0.08868347433,"remaining_time":0.1510015914},
{"learn":[138070.6427],"iteration":111,"passed_time":0.08958693463,"remaining_time":0.1503780688},
{"learn":[137838.311],"iteration":112,"passed_time":0.09038860542,"remaining_time":0.1495811435},
{"learn":[137580.4794],"iteration":113,"passed_time":0.09118448702,"remaining_time":0.1487746893},
{"learn":[137247.0489],"iteration":114,"passed_time":0.09171893371,"remaining_time":0.1475478499},
{"learn":[137092.1734],"iteration":115,"passed_time":0.0927227432,"remaining_time":0.1470774547},
{"learn":[136818.4774],"iteration":116,"passed_time":0.09345874822,"remaining_time":0.1461790677},
{"learn":[136658.7999],"iteration":117,"passed_time":0.09440523709,"remaining_time":0.1456080776},
{"learn":[136347.4333],"iteration":118,"passed_time":0.09525840948,"remaining_time":0.1448888413},
{"learn":[136207.1129],"iteration":119,"passed_time":0.09599328543,"remaining_time":0.1439899281},
{"learn":[136022.9008],"iteration":120,"passed_time":0.09666147017,"remaining_time":0.1429950674},
{"learn":[135840.5367],"iteration":121,"passed_time":0.09738666875,"remaining_time":0.1420887462},
{"learn":[135512.5731],"iteration":122,"passed_time":0.09814886031,"remaining_time":0.1412386039},
{"learn":[135245.6751],"iteration":123,"passed_time":0.09894718193,"remaining_time":0.1404411615},
{"learn":[135081.841],"iteration":124,"passed_time":0.09956066501,"remaining_time":0.139384931},
{"learn":[135009.8746],"iteration":125,"passed_time":0.1001565419,"remaining_time":0.138311415},
{"learn":[134783.4577],"iteration":126,"passed_time":0.1012241832,"remaining_time":0.1378880606},
{"learn":[134559.1896],"iteration":127,"passed_time":0.1019861959,"remaining_time":0.1370439507},
{"learn":[134387.7132],"iteration":128,"passed_time":0.1030209519,"remaining_time":0.1365626572},
{"learn":[134215.7339],"iteration":129,"passed_time":0.1037642677,"remaining_time":0.1356917347},
{"learn":[134055.3292],"iteration":130,"passed_time":0.1046235898,"remaining_time":0.1349724173},
{"learn":[133921.4049],"iteration":131,"passed_time":0.1055379285,"remaining_time":0.1343209999},
{"learn":[133744.2886],"iteration":132,"passed_time":0.1062443933,"remaining_time":0.1334046141},
{"learn":[133569.5491],"iteration":133,"passed_time":0.1072881647,"remaining_time":0.132909219},
{"learn":[133460.9512],"iteration":134,"passed_time":0.1080396878,"remaining_time":0.1320485073},
{"learn":[133296.246],"iteration":135,"passed_time":0.1089897636,"remaining_time":0.1314288326},
{"learn":[133107.2127],"iteration":136,"passed_time":0.109802851,"remaining_time":0.1306413483},
{"learn":[132810.9165],"iteration":137,"passed_time":0.1104561276,"remaining_time":0.1296658889},
{"learn":[132519.7332],"iteration":138,"passed_time":0.1113610055,"remaining_time":0.1289864883},
{"learn":[132316.8686],"iteration":139,"passed_time":0.1119870085,"remaining_time":0.1279851526},
{"learn":[132071.1837],"iteration":140,"passed_time":0.1129695704,"remaining_time":0.1273912177},
{"learn":[131784.4766],"iteration":141,"passed_time":0.1137155857,"remaining_time":0.1265286094},
{"learn":[131672.7851],"iteration":142,"passed_time":0.1144285122,"remaining_time":0.1256313036},
{"learn":[131371.108],"iteration":143,"passed_time":0.1154832011,"remaining_time":0.1251068012},
{"learn":[131084.3063],"iteration":144,"passed_time":0.1163367835,"remaining_time":0.12436001},
{"learn":[130940.475],"iteration":145,"passed_time":0.1170677486,"remaining_time":0.1234824197},
{"learn":[130846.3302],"iteration":146,"passed_time":0.1177729505,"remaining_time":0.1225800097},
{"learn":[130696.0565],"iteration":147,"passed_time":0.1183306047,"remaining_time":0.1215287292},
{"learn":[130573.9876],"iteration":148,"passed_time":0.1194417093,"remaining_time":0.1210449537},
{"learn":[130323.0668],"iteration":149,"passed_time":0.1201823375,"remaining_time":0.1201823375},
{"learn":[130067.3496],"iteration":150,"passed_time":0.1208579784,"remaining_time":0.1192572105},
{"learn":[129886.7016],"iteration":151,"passed_time":0.1213865714,"remaining_time":0.118192188},
{"learn":[129752.2319],"iteration":152,"passed_time":0.1222772348,"remaining_time":0.1174820491},
{"learn":[129600.5645],"iteration":153,"passed_time":0.1233821084,"remaining_time":0.1169726482},
{"learn":[129403.2178],"iteration":154,"passed_time":0.1240431005,"remaining_time":0.1160403198},
{"learn":[129325.1586],"iteration":155,"passed_time":0.1249334571,"remaining_time":0.1153231912},
{"learn":[129108.1729],"iteration":156,"passed_time":0.125680616,"remaining_time":0.1144734273},
{"learn":[128891.4698],"iteration":157,"passed_time":0.1268327742,"remaining_time":0.113988949},
{"learn":[128423.5939],"iteration":158,"passed_time":0.1274414112,"remaining_time":0.1130140816},
{"learn":[128267.9704],"iteration":159,"passed_time":0.1284048666,"remaining_time":0.1123542583},
{"learn":[128174.5984],"iteration":160,"passed_time":0.1289639141,"remaining_time":0.1113415159},
{"learn":[127998.2916],"iteration":161,"passed_time":0.1298090533,"remaining_time":0.1105780825},
{"learn":[127924.8244],"iteration":162,"passed_time":0.1307589749,"remaining_time":0.1099017151},
{"learn":[127754.0886],"iteration":163,"passed_time":0.1315589877,"remaining_time":0.1090976971},
{"learn":[127530.1628],"iteration":164,"passed_time":0.1321621459,"remaining_time":0.1081326648},
{"learn":[127497.4423],"iteration":165,"passed_time":0.1330158856,"remaining_time":0.1073742691},
{"learn":[127391.7868],"iteration":166,"passed_time":0.1336552522,"remaining_time":0.1064440032},
{"learn":[127284.9628],"iteration":167,"passed_time":0.1342690249,"remaining_time":0.105497091},
{"learn":[127182.7875],"iteration":168,"passed_time":0.1350932997,"remaining_time":0.1047172915},
{"learn":[127095.4056],"iteration":169,"passed_time":0.135519568,"remaining_time":0.1036326108},
{"learn":[126990.6466],"iteration":170,"passed_time":0.1361582151,"remaining_time":0.1027158465},
{"learn":[126878.7602],"iteration":171,"passed_time":0.1370208942,"remaining_time":0.1019690375},
{"learn":[126780.3228],"iteration":172,"passed_time":0.137803177,"remaining_time":0.1011618698},
{"learn":[126646.014],"iteration":173,"passed_time":0.1384570615,"remaining_time":0.1002620101},
{"learn":[126523.2193],"iteration":174,"passed_time":0.139171665,"remaining_time":0.09940833215},
{"learn":[126414.3335],"iteration":175,"passed_time":0.1397331847,"remaining_time":0.0984483801},
{"learn":[126400.4254],"iteration":176,"passed_time":0.1404728766,"remaining_time":0.09761674473},
{"learn":[126342.4364],"iteration":177,"passed_time":0.1414432842,"remaining_time":0.09694427341},
{"learn":[126202.3458],"iteration":178,"passed_time":0.1420854706,"remaining_time":0.09604660302},
{"learn":[126079.7987],"iteration":179,"passed_time":0.1427386864,"remaining_time":0.09515912425},
{"learn":[125945.7418],"iteration":180,"passed_time":0.1434389162,"remaining_time":0.09430514379},
{"learn":[125728.5804],"iteration":181,"passed_time":0.1442333239,"remaining_time":0.09351391331},
{"learn":[125607.4429],"iteration":182,"passed_time":0.1450570038,"remaining_time":0.0927413631},
{"learn":[125513.4912],"iteration":183,"passed_time":0.1457531114,"remaining_time":0.09188783109},
{"learn":[125158.3329],"iteration":184,"passed_time":0.1466411547,"remaining_time":0.09115531237},
{"learn":[125033.6545],"iteration":185,"passed_time":0.147279223,"remaining_time":0.09026791084},
{"learn":[124884.9438],"iteration":186,"passed_time":0.1478837153,"remaining_time":0.08936288676},
{"learn":[124723.324],"iteration":187,"passed_time":0.1489010545,"remaining_time":0.0887070112},
{"learn":[124569.0853],"iteration":188,"passed_time":0.1497155252,"remaining_time":0.08792816561},
{"learn":[124481.7349],"iteration":189,"passed_time":0.1505023199,"remaining_time":0.08713292203},
{"learn":[124372.3981],"iteration":190,"passed_time":0.1511184711,"remaining_time":0.08624038403},
{"learn":[124299.7456],"iteration":191,"passed_time":0.1518159683,"remaining_time":0.08539648216},
{"learn":[124193.9889],"iteration":192,"passed_time":0.1527401968,"remaining_time":0.08467979823},
{"learn":[124117.3149],"iteration":193,"passed_time":0.1536522945,"remaining_time":0.08395434648},
{"learn":[124008.6966],"iteration":194,"passed_time":0.1543560017,"remaining_time":0.08311477015},
{"learn":[123929.7169],"iteration":195,"passed_time":0.1549979701,"remaining_time":0.08224382086},
{"learn":[123745.883],"iteration":196,"passed_time":0.1559607478,"remaining_time":0.08154292907},
{"learn":[123593.5906],"iteration":197,"passed_time":0.1565879236,"remaining_time":0.08066650608},
{"learn":[123502.1173],"iteration":198,"passed_time":0.1574387204,"remaining_time":0.07990608422},
{"learn":[123386.8066],"iteration":199,"passed_time":0.1584225456,"remaining_time":0.07921127278},
{"learn":[123221.5829],"iteration":200,"passed_time":0.1590019938,"remaining_time":0.07831441486},
{"learn":[123046.8408],"iteration":201,"passed_time":0.1598102686,"remaining_time":0.07753171449},
{"learn":[122934.4596],"iteration":202,"passed_time":0.1607451068,"remaining_time":0.07680923822},
{"learn":[122852.15],"iteration":203,"passed_time":0.1618097821,"remaining_time":0.07614577983},
{"learn":[122711.6717],"iteration":204,"passed_time":0.1627382593,"remaining_time":0.07541529089},
{"learn":[122549.2432],"iteration":205,"passed_time":0.1635242205,"remaining_time":0.07461784817},
{"learn":[122512.6111],"iteration":206,"passed_time":0.1643412386,"remaining_time":0.0738344695},
{"learn":[122376.6949],"iteration":207,"passed_time":0.165205674,"remaining_time":0.07307174042},
{"learn":[122260.472],"iteration":208,"passed_time":0.1661127876,"remaining_time":0.07232662045},
{"learn":[122126.4705],"iteration":209,"passed_time":0.1667823202,"remaining_time":0.07147813725},
{"learn":[122012.0735],"iteration":210,"passed_time":0.1674451042,"remaining_time":0.07062850366},
{"learn":[121929.0263],"iteration":211,"passed_time":0.168175355,"remaining_time":0.06980863794},
{"learn":[121867.6933],"iteration":212,"passed_time":0.1687761746,"remaining_time":0.06893674738},
{"learn":[121790.2923],"iteration":213,"passed_time":0.1695820549,"remaining_time":0.06814979776},
{"learn":[121747.2123],"iteration":214,"passed_time":0.1704748638,"remaining_time":0.06739703919},
{"learn":[121658.3298],"iteration":215,"passed_time":0.1712719934,"remaining_time":0.06660577521},
{"learn":[121591.4595],"iteration":216,"passed_time":0.1723319557,"remaining_time":0.06591498765},
{"learn":[121377.4019],"iteration":217,"passed_time":0.1730680714,"remaining_time":0.06509899933},
{"learn":[121292.4864],"iteration":218,"passed_time":0.1739385488,"remaining_time":0.06433343584},
{"learn":[121204.7473],"iteration":219,"passed_time":0.1746604582,"remaining_time":0.06351289388},
{"learn":[121062.1153],"iteration":220,"passed_time":0.1755755494,"remaining_time":0.06276230048},
{"learn":[120952.0751],"iteration":221,"passed_time":0.1765596158,"remaining_time":0.0620344596},
{"learn":[120819.8482],"iteration":222,"passed_time":0.1772392775,"remaining_time":0.06119921242},
{"learn":[120759.6104],"iteration":223,"passed_time":0.1778883752,"remaining_time":0.06035498443},
{"learn":[120695.5391],"iteration":224,"passed_time":0.1785053036,"remaining_time":0.05950176786},
{"learn":[120592.9071],"iteration":225,"passed_time":0.179366722,"remaining_time":0.05873069657},
{"learn":[120565.9654],"iteration":226,"passed_time":0.1800657966,"remaining_time":0.05790662182},
{"learn":[120538.7841],"iteration":227,"passed_time":0.1808826541,"remaining_time":0.05712083812},
{"learn":[120499.8788],"iteration":228,"passed_time":0.1816898427,"remaining_time":0.05633178529},
{"learn":[120455.1558],"iteration":229,"passed_time":0.1826373242,"remaining_time":0.05558527259},
{"learn":[120447.9584],"iteration":230,"passed_time":0.1832776965,"remaining_time":0.05474528596},
{"learn":[120425.4619],"iteration":231,"passed_time":0.1841231999,"remaining_time":0.05396714479},
{"learn":[120329.62],"iteration":232,"passed_time":0.1851016242,"remaining_time":0.05322664731},
{"learn":[120121.7588],"iteration":233,"passed_time":0.1857122513,"remaining_time":0.05238037856},
{"learn":[120080.5117],"iteration":234,"passed_time":0.1863176218,"remaining_time":0.05153466134},
{"learn":[119792.5986],"iteration":235,"passed_time":0.1869189204,"remaining_time":0.05068987671},
{"learn":[119754.3838],"iteration":236,"passed_time":0.1878853581,"remaining_time":0.04994420913},
{"learn":[119694.8194],"iteration":237,"passed_time":0.1885892655,"remaining_time":0.04912829606},
{"learn":[119677.6409],"iteration":238,"passed_time":0.1894593627,"remaining_time":0.04835573692},
{"learn":[119647.9521],"iteration":239,"passed_time":0.1901471448,"remaining_time":0.04753678621},
{"learn":[119580.6432],"iteration":240,"passed_time":0.1911109961,"remaining_time":0.04678650942},
{"learn":[119451.8371],"iteration":241,"passed_time":0.1918184689,"remaining_time":0.04597302146},
{"learn":[119415.1544],"iteration":242,"passed_time":0.1927744208,"remaining_time":0.04521869129},
{"learn":[119318.6223],"iteration":243,"passed_time":0.1935158374,"remaining_time":0.04441347088},
{"learn":[119217.5656],"iteration":244,"passed_time":0.1943829779,"remaining_time":0.04363699504},
{"learn":[119041.9506],"iteration":245,"passed_time":0.1950241874,"remaining_time":0.04281018747},
{"learn":[118939.2197],"iteration":246,"passed_time":0.1959196115,"remaining_time":0.04203943081},
{"learn":[118901.008],"iteration":247,"passed_time":0.1967865477,"remaining_time":0.0412616955},
{"learn":[118882.2393],"iteration":248,"passed_time":0.197695946,"remaining_time":0.04049194074},
{"learn":[118865.7484],"iteration":249,"passed_time":0.1984698311,"remaining_time":0.03969396622},
{"learn":[118742.2485],"iteration":250,"passed_time":0.1992513256,"remaining_time":0.03889766915},
{"learn":[118666.9785],"iteration":251,"passed_time":0.2001695495,"remaining_time":0.03812753324},
{"learn":[118572.0575],"iteration":252,"passed_time":0.2007225473,"remaining_time":0.03728837835},
{"learn":[118441.0605],"iteration":253,"passed_time":0.2015258798,"remaining_time":0.03649681288},
{"learn":[118323.6029],"iteration":254,"passed_time":0.2023449175,"remaining_time":0.03570792661},
{"learn":[118237.4822],"iteration":255,"passed_time":0.20358314,"remaining_time":0.03499085218},
{"learn":[118229.6656],"iteration":256,"passed_time":0.2043192337,"remaining_time":0.03418570836},
{"learn":[118146.7484],"iteration":257,"passed_time":0.2049792824,"remaining_time":0.03336872039},
{"learn":[118038.7153],"iteration":258,"passed_time":0.2055649959,"remaining_time":0.03254117695},
{"learn":[117955.8745],"iteration":259,"passed_time":0.206255227,"remaining_time":0.03173157338},
{"learn":[117887.6925],"iteration":260,"passed_time":0.2071358085,"remaining_time":0.03095132771},
{"learn":[117862.9605],"iteration":261,"passed_time":0.207843641,"remaining_time":0.03014526091},
{"learn":[117821.4119],"iteration":262,"passed_time":0.2084560822,"remaining_time":0.02932652107},
{"learn":[117794.6798],"iteration":263,"passed_time":0.209458545,"remaining_time":0.02856252886},
{"learn":[117654.5726],"iteration":264,"passed_time":0.2104449853,"remaining_time":0.02779462071},
{"learn":[117637.7696],"iteration":265,"passed_time":0.21098305,"remaining_time":0.02696775827},
{"learn":[117594.859],"iteration":266,"passed_time":0.2117279186,"remaining_time":0.02616861916},
{"learn":[117546.0623],"iteration":267,"passed_time":0.2125512769,"remaining_time":0.02537925694},
{"learn":[117545.5707],"iteration":268,"passed_time":0.2129687243,"remaining_time":0.02454286414},
{"learn":[117508.5892],"iteration":269,"passed_time":0.2135879392,"remaining_time":0.02373199324},
{"learn":[117420.7855],"iteration":270,"passed_time":0.2142837221,"remaining_time":0.02293073041},
{"learn":[117367.8375],"iteration":271,"passed_time":0.2152393124,"remaining_time":0.02215698804},
{"learn":[117305.9906],"iteration":272,"passed_time":0.2161710925,"remaining_time":0.0213795586},
{"learn":[117216.6515],"iteration":273,"passed_time":0.2168717428,"remaining_time":0.02057907049},
{"learn":[117107.8042],"iteration":274,"passed_time":0.2174252177,"remaining_time":0.01976592888},
{"learn":[116978.6919],"iteration":275,"passed_time":0.2183375249,"remaining_time":0.01898587173},
{"learn":[116916.187],"iteration":276,"passed_time":0.2190052992,"remaining_time":0.01818455553},
{"learn":[116908.5466],"iteration":277,"passed_time":0.2198612982,"remaining_time":0.01739909554},
{"learn":[116837.2472],"iteration":278,"passed_time":0.2205977188,"remaining_time":0.01660412938},
{"learn":[116680.2257],"iteration":279,"passed_time":0.2214314694,"remaining_time":0.01581653353},
{"learn":[116674.609],"iteration":280,"passed_time":0.2222776113,"remaining_time":0.01502944703},
{"learn":[116618.9378],"iteration":281,"passed_time":0.2230224941,"remaining_time":0.01423547835},
{"learn":[116555.0925],"iteration":282,"passed_time":0.2236461187,"remaining_time":0.0134345725},
{"learn":[116471.4761],"iteration":283,"passed_time":0.2243725887,"remaining_time":0.01264070922},
{"learn":[116330.0249],"iteration":284,"passed_time":0.2254401987,"remaining_time":0.01186527362},
{"learn":[116274.595],"iteration":285,"passed_time":0.2262787201,"remaining_time":0.0110765807},
{"learn":[116161.8616],"iteration":286,"passed_time":0.2269150096,"remaining_time":0.01027838023},
{"learn":[116115.0512],"iteration":287,"passed_time":0.2277742243,"remaining_time":0.009490592679},
{"learn":[116104.5601],"iteration":288,"passed_time":0.2284768681,"remaining_time":0.008696351379},
{"learn":[116066.9846],"iteration":289,"passed_time":0.2292759587,"remaining_time":0.00790606754},
{"learn":[116006.305],"iteration":290,"passed_time":0.2299034825,"remaining_time":0.007110416986},
{"learn":[115935.8665],"iteration":291,"passed_time":0.2306572186,"remaining_time":0.006319375852},
{"learn":[115836.02],"iteration":292,"passed_time":0.2313292177,"remaining_time":0.005526636601},
{"learn":[115826.7714],"iteration":293,"passed_time":0.2320180562,"remaining_time":0.004735062372},
{"learn":[115770.1291],"iteration":294,"passed_time":0.2330291828,"remaining_time":0.003949647167},
{"learn":[115649.6753],"iteration":295,"passed_time":0.2337015297,"remaining_time":0.00315812878},
{"learn":[115566.0666],"iteration":296,"passed_time":0.2345915892,"remaining_time":0.002369612012},
{"learn":[115560.0988],"iteration":297,"passed_time":0.2356274553,"remaining_time":0.001581392318},
{"learn":[115483.5848],"iteration":298,"passed_time":0.2365030185,"remaining_time":0.0007909799951},
{"learn":[115479.0604],"iteration":299,"passed_time":0.2371883141,"remaining_time":0}
]}